purepress/__init__.py
purepress/__main__.py
purepress/__meta__.py
purepress_arts-0.5.0.dist-info/entry_points.txt
purepress_arts-0.5.0.dist-info/LICENSE
purepress_arts-0.5.0.dist-info/WHEEL
purepress_arts-0.5.0.dist-info/METADATA
purepress_arts-0.5.0.dist-info/RECORD
